odoo/addons/pos_session_sequence/README.rst
odoo/addons/pos_session_sequence/__init__.py
odoo/addons/pos_session_sequence/__manifest__.py
odoo/addons/pos_session_sequence/demo/pos_session_sequence.xml
odoo/addons/pos_session_sequence/i18n/ca.po
odoo/addons/pos_session_sequence/i18n/es.po
odoo/addons/pos_session_sequence/i18n/it.po
odoo/addons/pos_session_sequence/i18n/pos_session_sequence.pot
odoo/addons/pos_session_sequence/models/__init__.py
odoo/addons/pos_session_sequence/models/pos_config.py
odoo/addons/pos_session_sequence/models/pos_session.py
odoo/addons/pos_session_sequence/models/res_config_settings.py
odoo/addons/pos_session_sequence/readme/CONTRIBUTORS.md
odoo/addons/pos_session_sequence/readme/DESCRIPTION.md
odoo/addons/pos_session_sequence/readme/USAGE.md
odoo/addons/pos_session_sequence/static/description/icon.png
odoo/addons/pos_session_sequence/static/description/icon.svg
odoo/addons/pos_session_sequence/static/description/index.html
odoo/addons/pos_session_sequence/tests/__init__.py
odoo/addons/pos_session_sequence/tests/test_pos_session_sequence.py
odoo/addons/pos_session_sequence/views/res_config_settings_views.xml
odoo_addon_pos_session_sequence-17.0.1.0.0.4.dist-info/METADATA
odoo_addon_pos_session_sequence-17.0.1.0.0.4.dist-info/WHEEL
odoo_addon_pos_session_sequence-17.0.1.0.0.4.dist-info/top_level.txt
odoo_addon_pos_session_sequence-17.0.1.0.0.4.dist-info/RECORD
